README.md
setup.py
django_kapnoc/__init__.py
django_kapnoc/admin.py
django_kapnoc/apps.py
django_kapnoc/models.py
django_kapnoc/tests.py
django_kapnoc/urls.py
django_kapnoc/views.py
django_kapnoc.egg-info/PKG-INFO
django_kapnoc.egg-info/SOURCES.txt
django_kapnoc.egg-info/dependency_links.txt
django_kapnoc.egg-info/requires.txt
django_kapnoc.egg-info/top_level.txt
django_kapnoc/migrations/0001_initial.py
django_kapnoc/migrations/0002_auto_20201101_1732.py
django_kapnoc/migrations/0003_image_name_unique.py
django_kapnoc/migrations/__init__.py
django_kapnoc_tests/__init__.py
django_kapnoc_tests/asgi.py
django_kapnoc_tests/manage.py
django_kapnoc_tests/settings.py
django_kapnoc_tests/urls.py
django_kapnoc_tests/wsgi.py
django_kapnoc_tests2/__init__.py
django_kapnoc_tests2/admin.py
django_kapnoc_tests2/apps.py
django_kapnoc_tests2/models.py
django_kapnoc_tests2/tests.py
django_kapnoc_tests2/views.py
django_kapnoc_tests2/migrations/0001_initial.py
django_kapnoc_tests2/migrations/0002_auto_20201109_2030.py
django_kapnoc_tests2/migrations/__init__.py