Metadata-Version: 2.1
Name: django-kapnoc
Version: 0.0.6
Summary: Personnal helpers
Home-page: https://kapno.cc
Author: Tanguy Gérôme
Author-email: tanguy.gerome@gmail.com
License: BSD-3-Clause
Platform: UNKNOWN
Classifier: Programming Language :: Python :: 3
Classifier: License :: OSI Approved :: MIT License
Classifier: Operating System :: OS Independent
Classifier: Framework :: Django
Requires-Python: >=3.6
